
  [
    {
      "name": "Tops",
      "description": "Upper body garments including t-shirts, blouses, and shirts",
      "icon": "shirt",
      "subcategories": ["T-Shirts", "Blouses", "Shirts", "Sweaters", "Hoodies"],
      "featuredProducts": ["Classic White T-Shirt", "Men's Dress Shirt", "Knit Sweater"],
      "categoryImgUrl": "https://images.unsplash.com/photo-1523381210434-271e8be1f52b?w=800&auto=format&fit=crop"
    },
    {
      "name": "Bottoms",
      "description": "Lower body garments including pants, shorts, and skirts",
      "icon": "pants",
      "subcategories": ["Jeans", "Trousers", "Shorts", "Skirts", "Leggings"],
      "featuredProducts": ["Slim Fit Jeans", "High-Waisted Yoga Leggings"],
      "categoryImgUrl": "https://images.unsplash.com/photo-1541099649105-f69ad21f3246?w=800&auto=format&fit=crop"
    },
    {
      "name": "Dresses",
      "description": "One-piece garments for various occasions",
      "icon": "dress",
      "subcategories": ["Casual Dresses", "Formal Dresses", "Maxi Dresses", "Mini Dresses", "Sundresses"],
      "featuredProducts": ["Floral Summer Dress"],
      "categoryImgUrl": "https://images.unsplash.com/photo-1595777457583-95e059d581b8?w=800&auto=format&fit=crop"
    },
    {
      "name": "Outerwear",
      "description": "Garments worn over other clothes for warmth or style",
      "icon": "jacket",
      "subcategories": ["Jackets", "Coats", "Blazers", "Vests", "Cardigans"],
      "featuredProducts": ["Oversized Denim Jacket", "Men's Formal Suit"],
      "categoryImgUrl": "https://images.unsplash.com/photo-1551488831-00ddcb6c6bd3?w=800&auto=format&fit=crop"
    },
    {
      "name": "Accessories",
      "description": "Items that complement outfits such as bags, jewelry, and hats",
      "icon": "handbag",
      "subcategories": ["Bags", "Jewelry", "Hats", "Scarves", "Belts"],
      "featuredProducts": ["Wireless Noise-Cancelling Headphones", "Leather Crossbody Bag", "Straw Sun Hat", "Silk Scarf", "Leather Belt"],
      "categoryImgUrl": "https://images.unsplash.com/photo-1523779917675-b6ed3a42a561?w=800&auto=format&fit=crop"
    },
    {
      "name": "Footwear",
      "description": "Shoes and boots for all occasions",
      "icon": "shoe",
      "subcategories": ["Sneakers", "Boots", "Sandals", "Heels", "Flats"],
      "featuredProducts": ["Leather Ankle Boots", "Women's Running Shoes"],
      "categoryImgUrl": "https://images.unsplash.com/photo-1549298916-b41d501d3772?w=800&auto=format&fit=crop"
    },
    {
      "name": "Underwear",
      "description": "Undergarments and sleepwear",
      "icon": "underwear",
      "subcategories": ["Bras", "Panties", "Boxers", "Briefs", "Pajamas"],
      "featuredProducts": ["Cotton Pajama Set"],
      "categoryImgUrl": "https://images.unsplash.com/photo-1566336254703-c1ae8aea0cd6?w=800&auto=format&fit=crop"
    },
    {
      "name": "Activewear",
      "description": "Clothing designed for sports and exercise",
      "icon": "running",
      "subcategories": ["Workout Tops", "Workout Bottoms", "Sports Bras", "Swimwear", "Athletic Socks"],
      "featuredProducts": ["High-Waisted Yoga Leggings", "Men's Swim Shorts"],
      "categoryImgUrl": "https://images.unsplash.com/photo-1518459031867-a89b944bffe4?w=800&auto=format&fit=crop"
    },
    {
      "name": "Others",
      "description": "Miscellaneous items that don't fit into other categories",
      "icon": "more-horizontal",
      "subcategories": ["Costumes", "Uniforms", "Special Occasion Wear", "Maternity Wear"],
      "featuredProducts": [],
      "categoryImgUrl": "https://images.unsplash.com/photo-1567401893414-76b7b1e5a7a5?w=800&auto=format&fit=crop"
    }
  ]